{
  "slug": "reg-lac",
  "instrument_id": "urn:lex-mx:federal:regulation:reg-lac",
  "instrument_type": "regulation",
  "parser": "diputados",
  "official_title": "Reglamento de la Ley de Aviación Civil",
  "short_name": "REG-LAC",
  "operational_source": "camara_de_diputados",
  "source_url": "https://www.diputados.gob.mx/LeyesBiblio/regley/Reg_LAC.pdf",
  "reference_url": "https://www.diputados.gob.mx/LeyesBiblio/regley/Reg_LAC.pdf",
  "publisher": "Cámara de Diputados del H. Congreso de la Unión",
  "publication_date": "1998-12-07",
  "expected_min_articles": 290,
  "expected_articles": 290,
  "expected_transitories": 3,
  "count_baseline": {
    "provenance": "machine-proposed",
    "parser_version": "0.1.0",
    "proposed_at": "2026-07-12T08:04:17Z"
  },
  "allow_article_gaps": true,
  "formal_publication_urls": {}
}
