{
  "schema_version": "0.1.0",
  "id": "urn:lex-mx:federal:statute:lnsijpa",
  "jurisdiction": "mx",
  "level": "federal",
  "instrument_type": "statute",
  "official_title": "Ley Nacional del Sistema Integral de Justicia Penal para Adolescentes",
  "short_name": "LNSIJPA",
  "operational_source": "camara_de_diputados",
  "formal_publication_source": "dof",
  "publication_date": "2016-06-16",
  "latest_reform_date": "2022-12-20",
  "retrieved_at": "2026-07-12T06:57:20.135189Z",
  "source_url": "https://www.diputados.gob.mx/LeyesBiblio/pdf/LNSIJPA.pdf",
  "source_sha256": "8ab4065da6e313be48a524d93dfc9042fed41c2e5e0cf86c74894f58a18e218f",
  "extracted_text_sha256": "8c6858294f96ea3f0d2d788d9b8185439a71d7ddc2ae5c434536482ef4b4b9e9",
  "parser_version": "0.1.0",
  "status": "in_force"
}